setup.py
stat_dist/Binomialdistribution.py
stat_dist/Gaussiandistribution.py
stat_dist/Generaldistribution.py
stat_dist/__init__.py
stat_dist.egg-info/PKG-INFO
stat_dist.egg-info/SOURCES.txt
stat_dist.egg-info/dependency_links.txt
stat_dist.egg-info/not-zip-safe
stat_dist.egg-info/top_level.txt