Metadata-Version: 1.0
Name: stat-dist
Version: 0.2
Summary: Statistical distributions
Home-page: UNKNOWN
Author: UNKNOWN
Author-email: UNKNOWN
License: UNKNOWN
Platform: UNKNOWN
